README.md
setup.py
igni/__init__.py
igni/__main__.py
igni.egg-info/PKG-INFO
igni.egg-info/SOURCES.txt
igni.egg-info/dependency_links.txt
igni.egg-info/entry_points.txt
igni.egg-info/requires.txt
igni.egg-info/top_level.txt