Metadata-Version: 1.1
Name: igni
Version: 0.3.0
Summary: Client for gitignore.io with shell completions
Home-page: https://github.com/aweidner/igni
Author: Adam Weidner
Author-email: aweidner6993@gmail.com
License: MIT
Download-URL: https://github.com/aweidner/igni/archive/0.3.0.tar.gz
Keywords: gitignore,gitignore.io
Platform: UNKNOWN
Classifier: Development Status :: 3 - Alpha
Classifier: Intended Audience :: Developers
Classifier: Topic :: Software Development :: Build Tools
Classifier: License :: OSI Approved :: MIT License
Classifier: Programming Language :: Python :: 3
